[
	{
		"AttrId": 2101,
		"Item": "2005:150",
		"Level": 1,
		"Num": 50
	},
	{
		"AttrId": 2102,
		"Item": "2005:550",
		"Level": 2,
		"Num": 50
	},
	{
		"AttrId": 2103,
		"Item": "2005:1200",
		"Level": 3,
		"Num": 100
	},
	{
		"AttrId": 2104,
		"Item": "2005:2100",
		"Level": 4,
		"Num": 100
	},
	{
		"AttrId": 2105,
		"Item": "2005:3300",
		"Level": 5,
		"Num": 100
	},
	{
		"AttrId": 2106,
		"Item": "2005:4700",
		"Level": 6,
		"Num": 100
	},
	{
		"AttrId": 2107,
		"Item": "2005:6300",
		"Level": 7,
		"Num": 100
	},
	{
		"AttrId": 2108,
		"Item": "2005:8200",
		"Level": 8,
		"Num": 100
	},
	{
		"AttrId": 2109,
		"Item": "2005:10400",
		"Level": 9,
		"Num": 100
	},
	{
		"AttrId": 2110,
		"Item": "2005:12800",
		"Level": 10,
		"Num": 100
	},
	{
		"AttrId": 2111,
		"Item": "2005:15400",
		"Level": 11,
		"Num": 100
	},
	{
		"AttrId": 2112,
		"Item": "2005:18300",
		"Level": 12,
		"Num": 100
	},
	{
		"AttrId": 2113,
		"Item": "2005:21500",
		"Level": 13,
		"Num": 100
	},
	{
		"AttrId": 2114,
		"Item": "2005:24900",
		"Level": 14,
		"Num": 100
	},
	{
		"AttrId": 2115,
		"Item": "2005:28500",
		"Level": 15,
		"Num": 100
	},
	{
		"AttrId": 2116,
		"Item": "2005:32400",
		"Level": 16,
		"Num": 100
	},
	{
		"AttrId": 2117,
		"Item": "2005:36600",
		"Level": 17,
		"Num": 100
	},
	{
		"AttrId": 2118,
		"Item": "2005:41000",
		"Level": 18,
		"Num": 100
	},
	{
		"AttrId": 2119,
		"Item": "2005:45600",
		"Level": 19,
		"Num": 100
	},
	{
		"AttrId": 2120,
		"Item": "2005:50500",
		"Level": 20,
		"Num": 100
	}
]