[
	{
		"AttrPresent": 1500,
		"Desc1": "PVE伤加值+",
		"Desc2": "神灯属性加成",
		"Id": 1,
		"Level": 1,
		"Name": "智慧原石",
		"NeedItemId": 2150001,
		"NeedItemNum": 1,
		"Picture": 15000,
		"Pos": 1,
		"SkillDataID": 2304001,
		"SkillDesc": "500"
	},
	{
		"AttrPresent": 3000,
		"Desc1": "PVE伤加值+",
		"Desc2": "神灯属性加成",
		"Id": 2,
		"Level": 2,
		"Name": "智慧原石",
		"NeedItemId": 2150001,
		"NeedItemNum": 1,
		"Picture": 15000,
		"Pos": 1,
		"SkillDataID": 2304002,
		"SkillDesc": "550"
	},
	{
		"AttrPresent": 5000,
		"Desc1": "PVE伤加值+",
		"Desc2": "神灯属性加成",
		"Id": 3,
		"Level": 3,
		"Name": "智慧原石",
		"NeedItemId": 2150001,
		"NeedItemNum": 2,
		"Picture": 15000,
		"Pos": 1,
		"SkillDataID": 2304003,
		"SkillDesc": "600"
	},
	{
		"AttrPresent": 7500,
		"Desc1": "PVE伤加值+",
		"Desc2": "神灯属性加成",
		"Id": 4,
		"Level": 4,
		"Name": "智慧原石",
		"NeedItemId": 2150001,
		"NeedItemNum": 2,
		"Picture": 15000,
		"Pos": 1,
		"SkillDataID": 2304004,
		"SkillDesc": "650"
	},
	{
		"AttrPresent": 10000,
		"Desc1": "PVE伤加值+",
		"Desc2": "神灯属性加成",
		"Id": 5,
		"Level": 5,
		"Name": "智慧原石",
		"NeedItemId": 2150001,
		"NeedItemNum": 2,
		"Picture": 15000,
		"Pos": 1,
		"SkillDataID": 2304005,
		"SkillDesc": "700"
	},
	{
		"AttrPresent": 12500,
		"Desc1": "PVE伤加值+",
		"Desc2": "神灯属性加成",
		"Id": 6,
		"Level": 6,
		"Name": "智慧原石",
		"NeedItemId": 2150001,
		"NeedItemNum": 2,
		"Picture": 15000,
		"Pos": 1,
		"SkillDataID": 2304006,
		"SkillDesc": "750"
	},
	{
		"AttrPresent": 15500,
		"Desc1": "PVE伤加值+",
		"Desc2": "神灯属性加成",
		"Id": 7,
		"Level": 7,
		"Name": "智慧原石",
		"NeedItemId": 2150001,
		"NeedItemNum": 2,
		"Picture": 15000,
		"Pos": 1,
		"SkillDataID": 2304007,
		"SkillDesc": "800"
	},
	{
		"AttrPresent": 20000,
		"Desc1": "PVE伤加值+",
		"Desc2": "神灯属性加成",
		"Id": 8,
		"Level": 8,
		"Name": "智慧原石",
		"NeedItemId": 2150001,
		"NeedItemNum": 3,
		"Picture": 15000,
		"Pos": 1,
		"SkillDataID": 2304008,
		"SkillDesc": "850"
	},
	{
		"AttrPresent": 25000,
		"Desc1": "PVE伤加值+",
		"Desc2": "神灯属性加成",
		"Id": 9,
		"Level": 9,
		"Name": "智慧原石",
		"NeedItemId": 2150001,
		"NeedItemNum": 4,
		"Picture": 15000,
		"Pos": 1,
		"SkillDataID": 2304009,
		"SkillDesc": "900"
	},
	{
		"AttrPresent": 31700,
		"Desc1": "PVE伤加值+",
		"Desc2": "神灯属性加成",
		"Id": 10,
		"Level": 10,
		"Name": "智慧原石",
		"NeedItemId": 2150001,
		"NeedItemNum": 5,
		"Picture": 15000,
		"Pos": 1,
		"SkillDataID": 2304010,
		"SkillDesc": "1000"
	},
	{
		"AttrPresent": 1500,
		"Desc1": "PVP伤减值+",
		"Desc2": "神灯属性加成",
		"Id": 11,
		"Level": 1,
		"Name": "力量原石",
		"NeedItemId": 2150002,
		"NeedItemNum": 1,
		"Picture": 15001,
		"Pos": 2,
		"SkillDataID": 2305001,
		"SkillDesc": "500"
	},
	{
		"AttrPresent": 3000,
		"Desc1": "PVP伤减值+",
		"Desc2": "神灯属性加成",
		"Id": 12,
		"Level": 2,
		"Name": "力量原石",
		"NeedItemId": 2150002,
		"NeedItemNum": 1,
		"Picture": 15001,
		"Pos": 2,
		"SkillDataID": 2305002,
		"SkillDesc": "550"
	},
	{
		"AttrPresent": 5000,
		"Desc1": "PVP伤减值+",
		"Desc2": "神灯属性加成",
		"Id": 13,
		"Level": 3,
		"Name": "力量原石",
		"NeedItemId": 2150002,
		"NeedItemNum": 2,
		"Picture": 15001,
		"Pos": 2,
		"SkillDataID": 2305003,
		"SkillDesc": "600"
	},
	{
		"AttrPresent": 7500,
		"Desc1": "PVP伤减值+",
		"Desc2": "神灯属性加成",
		"Id": 14,
		"Level": 4,
		"Name": "力量原石",
		"NeedItemId": 2150002,
		"NeedItemNum": 2,
		"Picture": 15001,
		"Pos": 2,
		"SkillDataID": 2305004,
		"SkillDesc": "650"
	},
	{
		"AttrPresent": 10000,
		"Desc1": "PVP伤减值+",
		"Desc2": "神灯属性加成",
		"Id": 15,
		"Level": 5,
		"Name": "力量原石",
		"NeedItemId": 2150002,
		"NeedItemNum": 2,
		"Picture": 15001,
		"Pos": 2,
		"SkillDataID": 2305005,
		"SkillDesc": "700"
	},
	{
		"AttrPresent": 12500,
		"Desc1": "PVP伤减值+",
		"Desc2": "神灯属性加成",
		"Id": 16,
		"Level": 6,
		"Name": "力量原石",
		"NeedItemId": 2150002,
		"NeedItemNum": 2,
		"Picture": 15001,
		"Pos": 2,
		"SkillDataID": 2305006,
		"SkillDesc": "750"
	},
	{
		"AttrPresent": 15500,
		"Desc1": "PVP伤减值+",
		"Desc2": "神灯属性加成",
		"Id": 17,
		"Level": 7,
		"Name": "力量原石",
		"NeedItemId": 2150002,
		"NeedItemNum": 2,
		"Picture": 15001,
		"Pos": 2,
		"SkillDataID": 2305007,
		"SkillDesc": "800"
	},
	{
		"AttrPresent": 20000,
		"Desc1": "PVP伤减值+",
		"Desc2": "神灯属性加成",
		"Id": 18,
		"Level": 8,
		"Name": "力量原石",
		"NeedItemId": 2150002,
		"NeedItemNum": 3,
		"Picture": 15001,
		"Pos": 2,
		"SkillDataID": 2305008,
		"SkillDesc": "850"
	},
	{
		"AttrPresent": 25000,
		"Desc1": "PVP伤减值+",
		"Desc2": "神灯属性加成",
		"Id": 19,
		"Level": 9,
		"Name": "力量原石",
		"NeedItemId": 2150002,
		"NeedItemNum": 4,
		"Picture": 15001,
		"Pos": 2,
		"SkillDataID": 2305009,
		"SkillDesc": "900"
	},
	{
		"AttrPresent": 31700,
		"Desc1": "PVP伤减值+",
		"Desc2": "神灯属性加成",
		"Id": 20,
		"Level": 10,
		"Name": "力量原石",
		"NeedItemId": 2150002,
		"NeedItemNum": 5,
		"Picture": 15001,
		"Pos": 2,
		"SkillDataID": 2305010,
		"SkillDesc": "1000"
	},
	{
		"AttrPresent": 1500,
		"Desc1": "PVP伤加值+",
		"Desc2": "神灯属性加成",
		"Id": 21,
		"Level": 1,
		"Name": "勇气原石",
		"NeedItemId": 2150003,
		"NeedItemNum": 1,
		"Picture": 15002,
		"Pos": 3,
		"SkillDataID": 2306001,
		"SkillDesc": "500"
	},
	{
		"AttrPresent": 3000,
		"Desc1": "PVP伤加值+",
		"Desc2": "神灯属性加成",
		"Id": 22,
		"Level": 2,
		"Name": "勇气原石",
		"NeedItemId": 2150003,
		"NeedItemNum": 1,
		"Picture": 15002,
		"Pos": 3,
		"SkillDataID": 2306002,
		"SkillDesc": "550"
	},
	{
		"AttrPresent": 5000,
		"Desc1": "PVP伤加值+",
		"Desc2": "神灯属性加成",
		"Id": 23,
		"Level": 3,
		"Name": "勇气原石",
		"NeedItemId": 2150003,
		"NeedItemNum": 2,
		"Picture": 15002,
		"Pos": 3,
		"SkillDataID": 2306003,
		"SkillDesc": "600"
	},
	{
		"AttrPresent": 7500,
		"Desc1": "PVP伤加值+",
		"Desc2": "神灯属性加成",
		"Id": 24,
		"Level": 4,
		"Name": "勇气原石",
		"NeedItemId": 2150003,
		"NeedItemNum": 2,
		"Picture": 15002,
		"Pos": 3,
		"SkillDataID": 2306004,
		"SkillDesc": "650"
	},
	{
		"AttrPresent": 10000,
		"Desc1": "PVP伤加值+",
		"Desc2": "神灯属性加成",
		"Id": 25,
		"Level": 5,
		"Name": "勇气原石",
		"NeedItemId": 2150003,
		"NeedItemNum": 2,
		"Picture": 15002,
		"Pos": 3,
		"SkillDataID": 2306005,
		"SkillDesc": "700"
	},
	{
		"AttrPresent": 12500,
		"Desc1": "PVP伤加值+",
		"Desc2": "神灯属性加成",
		"Id": 26,
		"Level": 6,
		"Name": "勇气原石",
		"NeedItemId": 2150003,
		"NeedItemNum": 2,
		"Picture": 15002,
		"Pos": 3,
		"SkillDataID": 2306006,
		"SkillDesc": "750"
	},
	{
		"AttrPresent": 15500,
		"Desc1": "PVP伤加值+",
		"Desc2": "神灯属性加成",
		"Id": 27,
		"Level": 7,
		"Name": "勇气原石",
		"NeedItemId": 2150003,
		"NeedItemNum": 2,
		"Picture": 15002,
		"Pos": 3,
		"SkillDataID": 2306007,
		"SkillDesc": "800"
	},
	{
		"AttrPresent": 20000,
		"Desc1": "PVP伤加值+",
		"Desc2": "神灯属性加成",
		"Id": 28,
		"Level": 8,
		"Name": "勇气原石",
		"NeedItemId": 2150003,
		"NeedItemNum": 3,
		"Picture": 15002,
		"Pos": 3,
		"SkillDataID": 2306008,
		"SkillDesc": "850"
	},
	{
		"AttrPresent": 25000,
		"Desc1": "PVP伤加值+",
		"Desc2": "神灯属性加成",
		"Id": 29,
		"Level": 9,
		"Name": "勇气原石",
		"NeedItemId": 2150003,
		"NeedItemNum": 4,
		"Picture": 15002,
		"Pos": 3,
		"SkillDataID": 2306009,
		"SkillDesc": "900"
	},
	{
		"AttrPresent": 31700,
		"Desc1": "PVP伤加值+",
		"Desc2": "神灯属性加成",
		"Id": 30,
		"Level": 10,
		"Name": "勇气原石",
		"NeedItemId": 2150003,
		"NeedItemNum": 5,
		"Picture": 15002,
		"Pos": 3,
		"SkillDataID": 2306010,
		"SkillDesc": "1000"
	},
	{
		"AttrPresent": 1500,
		"Desc1": "PVE伤减值+",
		"Desc2": "神灯属性加成",
		"Id": 31,
		"Level": 1,
		"Name": "财富原石",
		"NeedItemId": 2150004,
		"NeedItemNum": 1,
		"Picture": 15003,
		"Pos": 4,
		"SkillDataID": 2307001,
		"SkillDesc": "500"
	},
	{
		"AttrPresent": 3000,
		"Desc1": "PVE伤减值+",
		"Desc2": "神灯属性加成",
		"Id": 32,
		"Level": 2,
		"Name": "财富原石",
		"NeedItemId": 2150004,
		"NeedItemNum": 1,
		"Picture": 15003,
		"Pos": 4,
		"SkillDataID": 2307002,
		"SkillDesc": "550"
	},
	{
		"AttrPresent": 5000,
		"Desc1": "PVE伤减值+",
		"Desc2": "神灯属性加成",
		"Id": 33,
		"Level": 3,
		"Name": "财富原石",
		"NeedItemId": 2150004,
		"NeedItemNum": 2,
		"Picture": 15003,
		"Pos": 4,
		"SkillDataID": 2307003,
		"SkillDesc": "600"
	},
	{
		"AttrPresent": 7500,
		"Desc1": "PVE伤减值+",
		"Desc2": "神灯属性加成",
		"Id": 34,
		"Level": 4,
		"Name": "财富原石",
		"NeedItemId": 2150004,
		"NeedItemNum": 2,
		"Picture": 15003,
		"Pos": 4,
		"SkillDataID": 2307004,
		"SkillDesc": "650"
	},
	{
		"AttrPresent": 10000,
		"Desc1": "PVE伤减值+",
		"Desc2": "神灯属性加成",
		"Id": 35,
		"Level": 5,
		"Name": "财富原石",
		"NeedItemId": 2150004,
		"NeedItemNum": 2,
		"Picture": 15003,
		"Pos": 4,
		"SkillDataID": 2307005,
		"SkillDesc": "700"
	},
	{
		"AttrPresent": 12500,
		"Desc1": "PVE伤减值+",
		"Desc2": "神灯属性加成",
		"Id": 36,
		"Level": 6,
		"Name": "财富原石",
		"NeedItemId": 2150004,
		"NeedItemNum": 2,
		"Picture": 15003,
		"Pos": 4,
		"SkillDataID": 2307006,
		"SkillDesc": "750"
	},
	{
		"AttrPresent": 15500,
		"Desc1": "PVE伤减值+",
		"Desc2": "神灯属性加成",
		"Id": 37,
		"Level": 7,
		"Name": "财富原石",
		"NeedItemId": 2150004,
		"NeedItemNum": 2,
		"Picture": 15003,
		"Pos": 4,
		"SkillDataID": 2307007,
		"SkillDesc": "800"
	},
	{
		"AttrPresent": 20000,
		"Desc1": "PVE伤减值+",
		"Desc2": "神灯属性加成",
		"Id": 38,
		"Level": 8,
		"Name": "财富原石",
		"NeedItemId": 2150004,
		"NeedItemNum": 3,
		"Picture": 15003,
		"Pos": 4,
		"SkillDataID": 2307008,
		"SkillDesc": "850"
	},
	{
		"AttrPresent": 25000,
		"Desc1": "PVE伤减值+",
		"Desc2": "神灯属性加成",
		"Id": 39,
		"Level": 9,
		"Name": "财富原石",
		"NeedItemId": 2150004,
		"NeedItemNum": 4,
		"Picture": 15003,
		"Pos": 4,
		"SkillDataID": 2307009,
		"SkillDesc": "900"
	},
	{
		"AttrPresent": 31700,
		"Desc1": "PVE伤减值+",
		"Desc2": "神灯属性加成",
		"Id": 40,
		"Level": 10,
		"Name": "财富原石",
		"NeedItemId": 2150004,
		"NeedItemNum": 5,
		"Picture": 15003,
		"Pos": 4,
		"SkillDataID": 2307010,
		"SkillDesc": "1000"
	},
	{
		"AttrPresent": 1500,
		"Desc1": "暴伤加成+",
		"Desc2": "神灯属性加成",
		"Id": 41,
		"Level": 1,
		"Name": "命运原石",
		"NeedItemId": 2150005,
		"NeedItemNum": 1,
		"Picture": 15004,
		"Pos": 5,
		"SkillDataID": 2308001,
		"SkillDesc": "500"
	},
	{
		"AttrPresent": 3000,
		"Desc1": "暴伤加成+",
		"Desc2": "神灯属性加成",
		"Id": 42,
		"Level": 2,
		"Name": "命运原石",
		"NeedItemId": 2150005,
		"NeedItemNum": 1,
		"Picture": 15004,
		"Pos": 5,
		"SkillDataID": 2308002,
		"SkillDesc": "550"
	},
	{
		"AttrPresent": 5000,
		"Desc1": "暴伤加成+",
		"Desc2": "神灯属性加成",
		"Id": 43,
		"Level": 3,
		"Name": "命运原石",
		"NeedItemId": 2150005,
		"NeedItemNum": 2,
		"Picture": 15004,
		"Pos": 5,
		"SkillDataID": 2308003,
		"SkillDesc": "600"
	},
	{
		"AttrPresent": 7500,
		"Desc1": "暴伤加成+",
		"Desc2": "神灯属性加成",
		"Id": 44,
		"Level": 4,
		"Name": "命运原石",
		"NeedItemId": 2150005,
		"NeedItemNum": 2,
		"Picture": 15004,
		"Pos": 5,
		"SkillDataID": 2308004,
		"SkillDesc": "650"
	},
	{
		"AttrPresent": 10000,
		"Desc1": "暴伤加成+",
		"Desc2": "神灯属性加成",
		"Id": 45,
		"Level": 5,
		"Name": "命运原石",
		"NeedItemId": 2150005,
		"NeedItemNum": 2,
		"Picture": 15004,
		"Pos": 5,
		"SkillDataID": 2308005,
		"SkillDesc": "700"
	},
	{
		"AttrPresent": 12500,
		"Desc1": "暴伤加成+",
		"Desc2": "神灯属性加成",
		"Id": 46,
		"Level": 6,
		"Name": "命运原石",
		"NeedItemId": 2150005,
		"NeedItemNum": 2,
		"Picture": 15004,
		"Pos": 5,
		"SkillDataID": 2308006,
		"SkillDesc": "750"
	},
	{
		"AttrPresent": 15500,
		"Desc1": "暴伤加成+",
		"Desc2": "神灯属性加成",
		"Id": 47,
		"Level": 7,
		"Name": "命运原石",
		"NeedItemId": 2150005,
		"NeedItemNum": 2,
		"Picture": 15004,
		"Pos": 5,
		"SkillDataID": 2308007,
		"SkillDesc": "800"
	},
	{
		"AttrPresent": 20000,
		"Desc1": "暴伤加成+",
		"Desc2": "神灯属性加成",
		"Id": 48,
		"Level": 8,
		"Name": "命运原石",
		"NeedItemId": 2150005,
		"NeedItemNum": 3,
		"Picture": 15004,
		"Pos": 5,
		"SkillDataID": 2308008,
		"SkillDesc": "850"
	},
	{
		"AttrPresent": 25000,
		"Desc1": "暴伤加成+",
		"Desc2": "神灯属性加成",
		"Id": 49,
		"Level": 9,
		"Name": "命运原石",
		"NeedItemId": 2150005,
		"NeedItemNum": 4,
		"Picture": 15004,
		"Pos": 5,
		"SkillDataID": 2308009,
		"SkillDesc": "900"
	},
	{
		"AttrPresent": 31700,
		"Desc1": "暴伤加成+",
		"Desc2": "神灯属性加成",
		"Id": 50,
		"Level": 10,
		"Name": "命运原石",
		"NeedItemId": 2150005,
		"NeedItemNum": 5,
		"Picture": 15004,
		"Pos": 5,
		"SkillDataID": 2308010,
		"SkillDesc": "1000"
	},
	{
		"AttrPresent": 1500,
		"Desc1": "生命值+",
		"Desc2": "神灯属性加成",
		"Id": 51,
		"Level": 1,
		"Name": "名利原石",
		"NeedItemId": 2150006,
		"NeedItemNum": 1,
		"Picture": 15005,
		"Pos": 6,
		"SkillDataID": 2309001,
		"SkillDesc": "500"
	},
	{
		"AttrPresent": 3000,
		"Desc1": "生命值+",
		"Desc2": "神灯属性加成",
		"Id": 52,
		"Level": 2,
		"Name": "名利原石",
		"NeedItemId": 2150006,
		"NeedItemNum": 1,
		"Picture": 15005,
		"Pos": 6,
		"SkillDataID": 2309002,
		"SkillDesc": "550"
	},
	{
		"AttrPresent": 5000,
		"Desc1": "生命值+",
		"Desc2": "神灯属性加成",
		"Id": 53,
		"Level": 3,
		"Name": "名利原石",
		"NeedItemId": 2150006,
		"NeedItemNum": 2,
		"Picture": 15005,
		"Pos": 6,
		"SkillDataID": 2309003,
		"SkillDesc": "600"
	},
	{
		"AttrPresent": 7500,
		"Desc1": "生命值+",
		"Desc2": "神灯属性加成",
		"Id": 54,
		"Level": 4,
		"Name": "名利原石",
		"NeedItemId": 2150006,
		"NeedItemNum": 2,
		"Picture": 15005,
		"Pos": 6,
		"SkillDataID": 2309004,
		"SkillDesc": "650"
	},
	{
		"AttrPresent": 10000,
		"Desc1": "生命值+",
		"Desc2": "神灯属性加成",
		"Id": 55,
		"Level": 5,
		"Name": "名利原石",
		"NeedItemId": 2150006,
		"NeedItemNum": 2,
		"Picture": 15005,
		"Pos": 6,
		"SkillDataID": 2309005,
		"SkillDesc": "700"
	},
	{
		"AttrPresent": 12500,
		"Desc1": "生命值+",
		"Desc2": "神灯属性加成",
		"Id": 56,
		"Level": 6,
		"Name": "名利原石",
		"NeedItemId": 2150006,
		"NeedItemNum": 2,
		"Picture": 15005,
		"Pos": 6,
		"SkillDataID": 2309006,
		"SkillDesc": "750"
	},
	{
		"AttrPresent": 15500,
		"Desc1": "生命值+",
		"Desc2": "神灯属性加成",
		"Id": 57,
		"Level": 7,
		"Name": "名利原石",
		"NeedItemId": 2150006,
		"NeedItemNum": 2,
		"Picture": 15005,
		"Pos": 6,
		"SkillDataID": 2309007,
		"SkillDesc": "800"
	},
	{
		"AttrPresent": 20000,
		"Desc1": "生命值+",
		"Desc2": "神灯属性加成",
		"Id": 58,
		"Level": 8,
		"Name": "名利原石",
		"NeedItemId": 2150006,
		"NeedItemNum": 3,
		"Picture": 15005,
		"Pos": 6,
		"SkillDataID": 2309008,
		"SkillDesc": "850"
	},
	{
		"AttrPresent": 25000,
		"Desc1": "生命值+",
		"Desc2": "神灯属性加成",
		"Id": 59,
		"Level": 9,
		"Name": "名利原石",
		"NeedItemId": 2150006,
		"NeedItemNum": 4,
		"Picture": 15005,
		"Pos": 6,
		"SkillDataID": 2309009,
		"SkillDesc": "900"
	},
	{
		"AttrPresent": 31700,
		"Desc1": "生命值+",
		"Desc2": "神灯属性加成",
		"Id": 60,
		"Level": 10,
		"Name": "名利原石",
		"NeedItemId": 2150006,
		"NeedItemNum": 5,
		"Picture": 15005,
		"Pos": 6,
		"SkillDataID": 2309010,
		"SkillDesc": "1000"
	}
]